sample_git_diffs/__init__.py
sample_git_diffs/sample_git_diffs.py
sample_git_diffs/to_md.py
sample_git_diffs-0.5.1.dist-info/METADATA
sample_git_diffs-0.5.1.dist-info/WHEEL
sample_git_diffs-0.5.1.dist-info/entry_points.txt
sample_git_diffs-0.5.1.dist-info/RECORD
