Metadata-Version: 2.1
Name: sample-git-diffs
Version: 0.5.1
Summary: 
Home-page: https://github.com/ninpnin/sample-git-diffs
License: MIT
Author: ninpnin
Author-email: you@example.com
Requires-Python: >=3.8,<4.0
Classifier: License :: OSI Approved :: MIT License
Classifier: Programming Language :: Python :: 3
Classifier: Programming Language :: Python :: 3.8
Classifier: Programming Language :: Python :: 3.9
Classifier: Programming Language :: Python :: 3.10
Classifier: Programming Language :: Python :: 3.11
Classifier: Programming Language :: Python :: 3.12
Classifier: Programming Language :: Python :: 3.13
Requires-Dist: pandas
Project-URL: Repository, https://github.com/ninpnin/sample-git-diffs
